varseries/__init__.py
varseries/varseries.py
varseries-2.0.3.dist-info/LICENCE
varseries-2.0.3.dist-info/METADATA
varseries-2.0.3.dist-info/WHEEL
varseries-2.0.3.dist-info/top_level.txt
varseries-2.0.3.dist-info/RECORD
