Metadata-Version: 2.1
Name: varseries
Version: 2.0.3
Summary: An utility to build and display variation series
Home-page: https://github.com/cyrillelamal/varseries
Author: Cyrille Kossyguine
Author-email: lambda_man@outlook.fr
License: MIT
Platform: UNKNOWN
Classifier: Programming Language :: Python :: 3
Classifier: License :: OSI Approved :: MIT License
Classifier: Operating System :: OS Independent
Requires-Python: >=3.6
Requires-Dist: plotly (>=4.3.0)
